odoo/addons/hr_employee_partner_external/README.rst
odoo/addons/hr_employee_partner_external/__init__.py
odoo/addons/hr_employee_partner_external/__manifest__.py
odoo/addons/hr_employee_partner_external/i18n/es.po
odoo/addons/hr_employee_partner_external/i18n/hr_employee_partner_external.pot
odoo/addons/hr_employee_partner_external/i18n/it.po
odoo/addons/hr_employee_partner_external/models/__init__.py
odoo/addons/hr_employee_partner_external/models/hr_employee.py
odoo/addons/hr_employee_partner_external/readme/CONTRIBUTORS.md
odoo/addons/hr_employee_partner_external/readme/DESCRIPTION.md
odoo/addons/hr_employee_partner_external/readme/HISTORY.md
odoo/addons/hr_employee_partner_external/readme/USAGE.md
odoo/addons/hr_employee_partner_external/static/description/icon.png
odoo/addons/hr_employee_partner_external/static/description/index.html
odoo/addons/hr_employee_partner_external/views/hr_employee.xml
odoo_addon_hr_employee_partner_external-18.0.1.0.0.2.dist-info/METADATA
odoo_addon_hr_employee_partner_external-18.0.1.0.0.2.dist-info/WHEEL
odoo_addon_hr_employee_partner_external-18.0.1.0.0.2.dist-info/top_level.txt
odoo_addon_hr_employee_partner_external-18.0.1.0.0.2.dist-info/RECORD
